<?xml version="1.0" encoding="UTF-8"?>
<objects serializationModel="Studio.02.02.00">
	<object class="AudioFile" id="{719d7583-d2d1-4d9c-a33e-e755f163e1f3}">
		<property name="assetPath">
			<value>Food &amp; Drink, Eating, Vegetable, Carrot, Bite, Chew, Close Up SND134547 2.wav</value>
		</property>
		<property name="frequencyInKHz">
			<value>48</value>
		</property>
		<property name="channelCount">
			<value>1</value>
		</property>
		<property name="length">
			<value>0.35841666666666666</value>
		</property>
		<relationship name="masterAssetFolder">
			<destination>{44f7c792-2f4a-436e-82be-bbb0c256c263}</destination>
		</relationship>
	</object>
</objects>
